[{"lat":55.71,"lng":4.74,"species":"Halichoerus grypus","commonName":"Gråsæl","date":"2016","protection":["Bilag II","Bilag V"],"id":3069556513},{"lat":55.71,"lng":4.74,"species":"Halichoerus grypus","commonName":"Gråsæl","date":"2016","protection":["Bilag II","Bilag V"],"id":3069556672},{"lat":55.7213,"lng":4.8017,"species":"Phocoena phocoena","commonName":"Marsvin","date":"2018","protection":["Bilag II","Bilag IV","Fredet"],"id":3069556417},{"lat":55.72,"lng":4.79,"species":"Phocoena phocoena","commonName":"Marsvin","date":"2018","protection":["Bilag II","Bilag IV","Fredet"],"id":3069556533},{"lat":55.6403,"lng":4.8842,"species":"Phocoena phocoena","commonName":"Marsvin","date":"2018","protection":["Bilag II","Bilag IV","Fredet"],"id":3069556586},{"lat":55.7213,"lng":4.8017,"species":"Phocoena phocoena","commonName":"Marsvin","date":"2016","protection":["Bilag II","Bilag IV","Fredet"],"id":3069556389},{"lat":55.5784,"lng":4.757,"species":"Phocoena phocoena","commonName":"Marsvin","date":"2016","protection":["Bilag II","Bilag IV","Fredet"],"id":3069556455},{"lat":55.5784,"lng":4.757,"species":"Phocoena phocoena","commonName":"Marsvin","date":"2016","protection":["Bilag II","Bilag IV","Fredet"],"id":3069556457},{"lat":55.5784,"lng":4.757,"species":"Phocoena phocoena","commonName":"Marsvin","date":"2016","protection":["Bilag II","Bilag IV","Fredet"],"id":3069556460},{"lat":55.71,"lng":4.74,"species":"Phocoena phocoena","commonName":"Marsvin","date":"2016","protection":["Bilag II","Bilag IV","Fredet"],"id":3069556464},{"lat":55.71,"lng":4.74,"species":"Phocoena phocoena","commonName":"Marsvin","date":"2016","protection":["Bilag II","Bilag IV","Fredet"],"id":3069556467},{"lat":55.7213,"lng":4.8017,"species":"Phocoena phocoena","commonName":"Marsvin","date":"2016","protection":["Bilag II","Bilag IV","Fredet"],"id":3069556538},{"lat":55.7213,"lng":4.8017,"species":"Phocoena phocoena","commonName":"Marsvin","date":"2016","protection":["Bilag II","Bilag IV","Fredet"],"id":3069556540},{"lat":55.7213,"lng":4.8017,"species":"Phocoena phocoena","commonName":"Marsvin","date":"2016","protection":["Bilag II","Bilag IV","Fredet"],"id":3069556564},{"lat":55.7213,"lng":4.8017,"species":"Phocoena phocoena","commonName":"Marsvin","date":"2016","protection":["Bilag II","Bilag IV","Fredet"],"id":3069556575},{"lat":55.8343,"lng":4.5614,"species":"Phocoena phocoena","commonName":"Marsvin","date":"2016","protection":["Bilag II","Bilag IV","Fredet"],"id":3069556579},{"lat":55.5784,"lng":4.757,"species":"Phocoena phocoena","commonName":"Marsvin","date":"2016","protection":["Bilag II","Bilag IV","Fredet"],"id":3069556648},{"lat":55.5784,"lng":4.757,"species":"Phocoena phocoena","commonName":"Marsvin","date":"2016","protection":["Bilag II","Bilag IV","Fredet"],"id":3069556650},{"lat":55.8343,"lng":4.5614,"species":"Phocoena phocoena","commonName":"Marsvin","date":"2016","protection":["Bilag II","Bilag IV","Fredet"],"id":3069556688},{"lat":55.7213,"lng":4.8017,"species":"Phocoena phocoena","commonName":"Marsvin","date":"2016","protection":["Bilag II","Bilag IV","Fredet"],"id":3069556718},{"lat":55.5784,"lng":4.757,"species":"Phocoena phocoena","commonName":"Marsvin","date":"2016","protection":["Bilag II","Bilag IV","Fredet"],"id":3069556728},{"lat":55.7213,"lng":4.8017,"species":"Phocoena phocoena","commonName":"Marsvin","date":"2016","protection":["Bilag II","Bilag IV","Fredet"],"id":3069556730},{"lat":55.579,"lng":4.758,"species":"Phocoena phocoena","commonName":"Marsvin","date":"2015","protection":["Bilag II","Bilag IV","Fredet"],"id":3069556395},{"lat":55.579,"lng":4.758,"species":"Phocoena phocoena","commonName":"Marsvin","date":"2015","protection":["Bilag II","Bilag IV","Fredet"],"id":3069556445},{"lat":55.579,"lng":4.758,"species":"Phocoena phocoena","commonName":"Marsvin","date":"2015","protection":["Bilag II","Bilag IV","Fredet"],"id":3069556555},{"lat":55.579,"lng":4.758,"species":"Phocoena phocoena","commonName":"Marsvin","date":"2015","protection":["Bilag II","Bilag IV","Fredet"],"id":3069556568},{"lat":55.7675,"lng":4.6483,"species":"Phocoena phocoena","commonName":"Marsvin","date":"2015","protection":["Bilag II","Bilag IV","Fredet"],"id":3069556580},{"lat":55.579,"lng":4.758,"species":"Lagenorhynchus albirostris","commonName":"Hvidnæse","date":"2016","protection":["Bilag IV","Fredet"],"id":3069556450},{"lat":55.579,"lng":4.758,"species":"Lagenorhynchus albirostris","commonName":"Hvidnæse","date":"2016","protection":["Bilag IV","Fredet"],"id":3069556451},{"lat":55.7213,"lng":4.8017,"species":"Lagenorhynchus albirostris","commonName":"Hvidnæse","date":"2016","protection":["Bilag IV","Fredet"],"id":3069556475},{"lat":55.7213,"lng":4.8017,"species":"Lagenorhynchus albirostris","commonName":"Hvidnæse","date":"2016","protection":["Bilag IV","Fredet"],"id":3069556510},{"lat":55.579,"lng":4.758,"species":"Lagenorhynchus albirostris","commonName":"Hvidnæse","date":"2015","protection":["Bilag IV","Fredet"],"id":3069556491},{"lat":55.579,"lng":4.758,"species":"Lagenorhynchus albirostris","commonName":"Hvidnæse","date":"2015","protection":["Bilag IV","Fredet"],"id":3069556492},{"lat":55.71,"lng":4.74,"species":"Lagenorhynchus albirostris","commonName":"Hvidnæse","date":"2014","protection":["Bilag IV","Fredet"],"id":3069556388},{"lat":55.6549,"lng":4.778,"species":"Lagenorhynchus albirostris","commonName":"Hvidnæse","date":"2014","protection":["Bilag IV","Fredet"],"id":3069556711},{"lat":55.7095,"lng":4.5105,"species":"Lagenorhynchus albirostris","commonName":"Hvidnæse","date":"2001-05-13","protection":["Bilag IV","Fredet"],"id":1413744435},{"lat":55.7095,"lng":4.5105,"species":"Lagenorhynchus albirostris","commonName":"Hvidnæse","date":"2001-05-13","protection":["Bilag IV","Fredet"],"id":1413744457},{"lat":55.8871,"lng":4.6773,"species":"Lagenorhynchus albirostris","commonName":"Hvidnæse","date":"2001-06-26","protection":["Bilag IV","Fredet"],"id":1413744441},{"lat":55.8871,"lng":4.6773,"species":"Lagenorhynchus albirostris","commonName":"Hvidnæse","date":"2001-06-26","protection":["Bilag IV","Fredet"],"id":1413744454},{"lat":55.8871,"lng":4.6773,"species":"Lagenorhynchus albirostris","commonName":"Hvidnæse","date":"2001-06-26","protection":["Bilag IV","Fredet"],"id":1413744475},{"lat":55.8871,"lng":4.6773,"species":"Lagenorhynchus albirostris","commonName":"Hvidnæse","date":"2001-06-26","protection":["Bilag IV","Fredet"],"id":1413744526},{"lat":55.74,"lng":4.67,"species":"Lagenorhynchus albirostris","commonName":"Hvidnæse","date":"1991-10-30","protection":["Bilag IV","Fredet"],"id":4114461342},{"lat":55.8985,"lng":4.278,"species":"Balaenoptera acutorostrata","commonName":"Vågehval","date":"2016","protection":["Bilag IV","Fredet"],"id":5790919738},{"lat":55.9967,"lng":4.0383,"species":"Balaenoptera acutorostrata","commonName":"Vågehval","date":"2007-05-12","protection":["Bilag IV","Fredet"],"id":4130696338},{"lat":55.76,"lng":4.75,"species":"Balaenoptera acutorostrata","commonName":"Vågehval","date":"2005-07-08","protection":["Bilag IV","Fredet"],"id":3085355603},{"lat":55.7596,"lng":4.7552,"species":"Balaenoptera acutorostrata","commonName":"Vågehval","date":"2005-07-08","protection":["Bilag IV","Fredet"],"id":4113574617},{"lat":55.5231,"lng":4.9786,"species":"Balaenoptera acutorostrata","commonName":"Vågehval","date":"2002-08","protection":["Bilag IV","Fredet"],"id":1413744510},{"lat":55.7973,"lng":4.6734,"species":"Balaenoptera acutorostrata","commonName":"Vågehval","date":"2001-05-25","protection":["Bilag IV","Fredet"],"id":1413744494},{"lat":55.5278,"lng":4.6619,"species":"Balaenoptera acutorostrata","commonName":"Vågehval","date":"2001-06-26","protection":["Bilag IV","Fredet"],"id":1413744486},{"lat":55.5231,"lng":4.9786,"species":"Balaenoptera acutorostrata","commonName":"Vågehval","date":"2001-06-26","protection":["Bilag IV","Fredet"],"id":1413744499},{"lat":55.5231,"lng":4.9786,"species":"Balaenoptera acutorostrata","commonName":"Vågehval","date":"2001-06-26","protection":["Bilag IV","Fredet"],"id":1413744553},{"lat":55.5231,"lng":4.9786,"species":"Balaenoptera acutorostrata","commonName":"Vågehval","date":"2001-07-02","protection":["Bilag IV","Fredet"],"id":1413744464},{"lat":55.5231,"lng":4.9786,"species":"Balaenoptera acutorostrata","commonName":"Vågehval","date":"2001-07-29","protection":["Bilag IV","Fredet"],"id":1413744471},{"lat":55.5231,"lng":4.9786,"species":"Balaenoptera acutorostrata","commonName":"Vågehval","date":"2001-07-28","protection":["Bilag IV","Fredet"],"id":1413744489},{"lat":55.5231,"lng":4.9786,"species":"Balaenoptera acutorostrata","commonName":"Vågehval","date":"2001-07-26","protection":["Bilag IV","Fredet"],"id":1413744504},{"lat":55.71,"lng":4.74,"species":"Globicephala melas","commonName":"Grindehval","date":"2016","protection":["Bilag IV","Fredet"],"id":3069556307}]